pytemplify/__init__.py
pytemplify/base_classes.py
pytemplify/exceptions.py
pytemplify/file_uri_utils.py
pytemplify/logging_utils.py
pytemplify/main.py
pytemplify/manual_sections.py
pytemplify/parser_loader.py
pytemplify/pattern_matcher.py
pytemplify/py.typed
pytemplify/renderer.py
pytemplify/data_helpers/__init__.py
pytemplify/data_helpers/base.py
pytemplify/data_helpers/context.py
pytemplify/data_helpers/loader.py
pytemplify/data_helpers/ordering.py
pytemplify/data_helpers/proxy.py
pytemplify/data_helpers/smart_dict.py
pytemplify/data_helpers/wrapper.py
pytemplify/filters/__init__.py
pytemplify/filters/collection_filters.py
pytemplify/filters/formatting_filters.py
pytemplify/filters/string_filters.py
pytemplify/filters/utility_filters.py
pytemplify/formatting/__init__.py
pytemplify/formatting/base.py
pytemplify/formatting/builtin.py
pytemplify/formatting/command.py
pytemplify/formatting/manager.py
pytemplify/formatting/formatters/__init__.py
pytemplify/formatting/formatters/black.py
pytemplify/formatting/formatters/clang.py
pytemplify/formatting/formatters/prettier.py
pytemplify/generator/__init__.py
pytemplify/generator/base_generator.py
pytemplify/generator/config_file_loader.py
pytemplify/generator/generation_helpers.py
pytemplify/generator/generic_generator.py
pytemplify/generator/path_resolver.py
pytemplify/generator/renderer_configurator.py
pytemplify/generator/schema_validator.py
pytemplify/generator/template_config.py
pytemplify/generator/templates-schema.json
pytemplify/generator/utils.py
pytemplify/generator/validation_integration.py
pytemplify/validation/__init__.py
pytemplify/validation/base.py
pytemplify/validation/cmake_manager.py
pytemplify/validation/interactive.py
pytemplify/validation/project_scanner.py
pytemplify/validation/registry.py
pytemplify/validation/runner.py
pytemplify/validation/schema.py
pytemplify/validation/templates/gtest/CMakeLists.txt.j2
pytemplify/validation/templates/gtest/CMakeLists_batch.txt.j2
pytemplify-0.2.6.dist-info/licenses/LICENSE
pytemplify-0.2.6.dist-info/METADATA
pytemplify-0.2.6.dist-info/WHEEL
pytemplify-0.2.6.dist-info/entry_points.txt
pytemplify-0.2.6.dist-info/top_level.txt
pytemplify-0.2.6.dist-info/RECORD
