Metadata-Version: 2.4
Name: pytemplify
Version: 0.2.6
Summary: A generic generator framework using Jinja2 and user-defined parsers.
Author-email: robinbreast <kihoa.nam@gmail.com>
License: MIT
Requires-Python: >=3.8.1
License-File: LICENSE
Requires-Dist: jinja2>=3.1.2
Requires-Dist: dataclasses-jsonschema>=2.16.0
Requires-Dist: pyyaml>=6.0.0
Requires-Dist: jsonschema>=4.0.0
Requires-Dist: black>=23.3.0
Requires-Dist: prettier>=0.0.1
Requires-Dist: clang-format>=17.0.0
Requires-Dist: click>=8.0.0
Requires-Dist: questionary>=1.10.0
Requires-Dist: gcovr>=7.0
Requires-Dist: colorama>=0.4.6
Provides-Extra: dev
Requires-Dist: pytest>=8.3.5; extra == "dev"
Requires-Dist: pytest-snapshot>=0.9.0; extra == "dev"
Requires-Dist: pytest-cov>=5.0.0; extra == "dev"
Requires-Dist: flake8>=6.0.0; extra == "dev"
Requires-Dist: isort>=5.12.0; extra == "dev"
Requires-Dist: nox>=2025.2.9; extra == "dev"
Dynamic: license-file
